ffmpeg_win64/__init__.py
ffmpeg_win64-0.0.2.dist-info/METADATA
ffmpeg_win64-0.0.2.dist-info/WHEEL
ffmpeg_win64-0.0.2.dist-info/top_level.txt
ffmpeg_win64-0.0.2.dist-info/RECORD
